mdfb/__init__.py
mdfb/core/download_blobs.py
mdfb/core/fetch_post_details.py
mdfb/core/get_feed_details.py
mdfb/core/get_post_identifiers.py
mdfb/core/resolve_handle.py
mdfb/mdfb.py
mdfb/utils/cli_helpers.py
mdfb/utils/constants.py
mdfb/utils/database.py
mdfb/utils/helpers.py
mdfb/utils/logging.py
mdfb/utils/login.py
mdfb/utils/validation.py
mdfb-1.6.2.dist-info/METADATA
mdfb-1.6.2.dist-info/WHEEL
mdfb-1.6.2.dist-info/entry_points.txt
mdfb-1.6.2.dist-info/licenses/LICENSE
mdfb-1.6.2.dist-info/RECORD
