Metadata-Version: 2.4
Name: mdfb
Version: 1.6.2
Summary: A CLI for downloading posts in bulk from Bluesky from a specified account
License-File: LICENSE
Author: Ibrahim Haji Abdi
Author-email: ibrahim.hajiabdi09@gmail.com
Requires-Python: >3.9.1,<3.14
Classifier: Programming Language :: Python :: 3
Classifier: License :: OSI Approved :: MIT License
Classifier: Operating System :: OS Independent
Classifier: Environment :: Console
Requires-Dist: argparse (>=1.4.0,<2.0.0)
Requires-Dist: atproto (>=0.0.55,<0.0.56)
Requires-Dist: h11 (>=0.16.0,<0.17.0)
Requires-Dist: httpcore (>=1.0.9,<2.0.0)
Requires-Dist: pathvalidate (>=3.2.1,<4.0.0)
Requires-Dist: platformdirs (>=4.3.7,<5.0.0)
Requires-Dist: psutil (>=7.0.0,<8.0.0)
Requires-Dist: pyyaml (>=6.0.3,<7.0.0)
Requires-Dist: tenacity (>=9.0.0,<10.0.0)
Requires-Dist: tqdm (>=4.67.1,<5.0.0)
Project-URL: Issues, https://github.com/IbrahimHajiAbdi/mass-downloader-for-bluesky/issues
Project-URL: Repository, https://github.com/IbrahimHajiAbdi/mass-downloader-for-bluesky.git
